SessizMuezzin/__init__.py
SessizMuezzin/pyramid_first_last.py
SessizMuezzin/sequences_first_last.py
sessizmuezzin-0.0.2.dist-info/licenses/LICENSE.txt
sessizmuezzin-0.0.2.dist-info/METADATA
sessizmuezzin-0.0.2.dist-info/WHEEL
sessizmuezzin-0.0.2.dist-info/top_level.txt
sessizmuezzin-0.0.2.dist-info/RECORD
