Metadata-Version: 2.4
Name: SessizMuezzin
Version: 0.0.2
Summary: Python programming course assignments and solutions.
Author-email: SessizMuezzin <your.email@example.com>
Project-URL: Homepage, https://github.com/SessizMuezzin/SessizMuezzin
Keywords: python,education,programming,assignments
Classifier: Development Status :: 3 - Alpha
Classifier: Intended Audience :: Developers
Classifier: License :: OSI Approved :: MIT License
Classifier: Programming Language :: Python :: 3
Classifier: Operating System :: OS Independent
Requires-Python: >=3.6
License-File: LICENSE.txt
Dynamic: license-file
